Minter/__init__.py
Minter/minter.py
Minter/transaction_builder.py
Minter/utils.py
Minter/data/nft_abi.json
Minter/data/opensea_abi.json
Minter/storage/__init__.py
Minter/storage/base_storage.py
Minter/storage/basic_storage.py
Minter/storage/memory_storage.py
Minter/types/__init__.py
Minter/types/nft_data.py
Minter/types/wallet.py
Minter/types/abis/__init__.py
Minter/types/abis/abi.py
Minter/types/abis/opensea.py
minter-1.0.6.dist-info/licenses/LICENSE
minter-1.0.6.dist-info/METADATA
minter-1.0.6.dist-info/WHEEL
minter-1.0.6.dist-info/top_level.txt
minter-1.0.6.dist-info/RECORD
