Metadata-Version: 2.4
Name: minter
Version: 1.0.6
Summary: a lib to mint nft's on any EVM chain
Author: SpicyPenguin
Requires-Python: >=3.8
License-File: LICENSE
Requires-Dist: kvsqlite
Requires-Dist: web3
Dynamic: license-file
